precice_case_generate-0.1.1.dist-info/licenses/LICENSE
precicecasegenerate/cli.py
precicecasegenerate/controller_utils/myutils/UT_PCErrorLogging.py
precicecasegenerate/controller_utils/myutils/__init__.py
precicecasegenerate/controller_utils/precice_struct/PS_CouplingScheme.py
precicecasegenerate/controller_utils/precice_struct/PS_Mesh.py
precicecasegenerate/controller_utils/precice_struct/PS_ParticipantSolver.py
precicecasegenerate/controller_utils/precice_struct/PS_PreCICEConfig.py
precicecasegenerate/controller_utils/precice_struct/PS_QuantityCoupled.py
precicecasegenerate/controller_utils/precice_struct/__init__.py
precicecasegenerate/controller_utils/ui_struct/UI_Coupling.py
precicecasegenerate/controller_utils/ui_struct/UI_Participant.py
precicecasegenerate/controller_utils/ui_struct/UI_SimulationInfo.py
precicecasegenerate/controller_utils/ui_struct/UI_UserInput.py
precicecasegenerate/controller_utils/ui_struct/__init__.py
precicecasegenerate/generation_utils/__init__.py
precicecasegenerate/generation_utils/adapter_config_generator.py
precicecasegenerate/generation_utils/config_generator.py
precicecasegenerate/generation_utils/file_generator.py
precicecasegenerate/generation_utils/format_precice_config.py
precicecasegenerate/generation_utils/logger.py
precicecasegenerate/generation_utils/other_files_generator.py
precicecasegenerate/generation_utils/readme_generator.py
precicecasegenerate/generation_utils/structure_handler.py
precicecasegenerate/schemas/README.md
precicecasegenerate/schemas/topology-schema.json
precicecasegenerate/templates/adapter-config-template.json
precicecasegenerate/templates/metaConfiguratorSettings.json
precicecasegenerate/templates/template_README.md
precicecasegenerate/templates/template_clean.sh
precicecasegenerate/templates/template_run.sh
precice_case_generate-0.1.1.dist-info/METADATA
precice_case_generate-0.1.1.dist-info/WHEEL
precice_case_generate-0.1.1.dist-info/entry_points.txt
precice_case_generate-0.1.1.dist-info/top_level.txt
precice_case_generate-0.1.1.dist-info/RECORD
