Metadata-Version: 2.4
Name: precice-case-generate
Version: 0.1.1
Summary: Generates File and Folder Structure, including all of the necessary files to quickly kickstart a simulation
Author-email: VanLaareN <vanlaren@example.com>, Toddelismyname <116207910+Toddelismyname@users.noreply.github.com>
License-Expression: MIT
Project-URL: Repository, https://github.com/precice-forschungsprojekt/precice-generator
Project-URL: Issues, https://github.com/precice-forschungsprojekt/precice-generator/issues
Project-URL: Documentation, https://github.com/precice-forschungsprojekt/precice-generator/blob/main/README.md
Requires-Python: >=3.9
License-File: LICENSE
Requires-Dist: attrs>=25.3
Requires-Dist: jsonschema>=4.23
Requires-Dist: jsonschema-specifications>=2024.10
Requires-Dist: lxml>=5.3
Requires-Dist: ruamel_yaml
Requires-Dist: referencing>=0.36
Requires-Dist: rpds-py>=0.24
Requires-Dist: termcolor>=3
Requires-Dist: typing_extensions>=4.13
Dynamic: license-file
